{"apiVersion":"1.0","apis":[{"path":"/overTheBox","operations":[{"apiStatus":{"description":"Stable production version","value":"PRODUCTION"},"httpMethod":"GET","parameters":[],"responseType":"string[]","noAuthentication":false,"description":"List available services","iamActions":["overTheBox:apiovh:get"]}],"description":"Operations about the OVERTHEBOX service"},{"path":"/overTheBox/availableOffers","operations":[{"apiStatus":{"description":"Stable production version","value":"PRODUCTION"},"httpMethod":"GET","parameters":[],"responseType":"price.OverTheBox.OfferEnum[]","noAuthentication":false,"description":"List the available offers for the new call","iamActions":["account:apiovh:overTheBox/availableOffers/get"]}],"description":"List the available offers for the new call"},{"path":"/overTheBox/devices","operations":[{"apiStatus":{"description":"Stable production version","value":"PRODUCTION"},"httpMethod":"POST","parameters":[],"responseType":"overTheBox.DeviceForRegistration[]","noAuthentication":false,"description":"Get the list of devices connected from the same IP address","iamActions":["account:apiovh:overTheBox/devices/create"]}],"description":"Get the list of devices connected from the same IP address"},{"path":"/overTheBox/hardware","operations":[{"apiStatus":{"description":"Stable production version","value":"PRODUCTION"},"httpMethod":"GET","parameters":[],"responseType":"string[]","noAuthentication":false,"description":"List available services","iamActions":["overTheBoxHardware:apiovh:get"]}],"description":"Operations about the OVERTHEBOX service"},{"path":"/overTheBox/hardware/available","operations":[{"apiStatus":{"description":"Stable production version","value":"PRODUCTION"},"httpMethod":"GET","parameters":[],"responseType":"string[]","noAuthentication":false,"description":"List hardware that can be linked to a service","iamActions":["account:apiovh:overTheBoxHardware/available/get"]}],"description":"List hardware that can be linked to a service"},{"path":"/overTheBox/hardware/{hardwareName}","operations":[{"apiStatus":{"description":"Stable production version","value":"PRODUCTION"},"httpMethod":"GET","parameters":[{"name":"hardwareName","dataType":"string","paramType":"path","fullType":"string","required":true,"description":"The internal name of your hardware"}],"responseType":"overTheBox.Hardware","noAuthentication":false,"description":"Get this object properties","iamActions":["overTheBoxHardware:apiovh:get"]}],"description":"Hardware properties"},{"path":"/overTheBox/{serviceName}","operations":[{"apiStatus":{"description":"Stable production version","value":"PRODUCTION"},"httpMethod":"DELETE","parameters":[{"name":"serviceName","dataType":"string","paramType":"path","fullType":"string","required":true,"description":"The internal name of your overTheBox offer"}],"responseType":"void","noAuthentication":false,"description":"Resiliate a service","iamActions":["overTheBox:apiovh:delete"]},{"apiStatus":{"description":"Stable production version","value":"PRODUCTION"},"httpMethod":"GET","parameters":[{"name":"serviceName","dataType":"string","paramType":"path","fullType":"string","required":true,"description":"The internal name of your overTheBox offer"}],"responseType":"overTheBox.Service","noAuthentication":false,"description":"Get this object properties","iamActions":["overTheBox:apiovh:get"]},{"apiStatus":{"description":"Stable production version","value":"PRODUCTION"},"httpMethod":"PUT","parameters":[{"dataType":"overTheBox.Service","paramType":"body","fullType":"overTheBox.Service","required":true,"description":"New object properties"},{"name":"serviceName","dataType":"string","paramType":"path","fullType":"string","required":true,"description":"The internal name of your overTheBox offer"}],"responseType":"void","noAuthentication":false,"description":"Alter this object properties","iamActions":["overTheBox:apiovh:put"]}],"description":"Service"},{"path":"/overTheBox/{serviceName}/autoMTU","operations":[{"apiStatus":{"description":"Stable production version","value":"PRODUCTION"},"httpMethod":"PUT","parameters":[{"name":"mtuAuto","dataType":"overTheBox.AvailableStatusEnum","paramType":"body","fullType":"overTheBox.AvailableStatusEnum","required":true,"description":"Enable or disable autoMTU"},{"name":"serviceName","dataType":"string","paramType":"path","fullType":"string","required":true,"description":"The internal name of your overTheBox offer"}],"responseType":"void","noAuthentication":false,"description":"Change the value of autoMTU","iamActions":["overTheBox:apiovh:autoMTU/edit"]}],"description":"autoMTU operations"},{"path":"/overTheBox/{serviceName}/availableReleaseChannels","operations":[{"apiStatus":{"description":"Stable production version","value":"PRODUCTION"},"httpMethod":"GET","parameters":[{"name":"serviceName","dataType":"string","paramType":"path","fullType":"string","required":true,"description":"The internal name of your overTheBox offer"}],"responseType":"string[]","noAuthentication":false,"description":"List available release channels for this service","iamActions":["overTheBox:apiovh:availableReleaseChannels/get"]}],"description":"availableReleaseChannels operations"},{"path":"/overTheBox/{serviceName}/backups","operations":[{"apiStatus":{"description":"Stable production version","value":"PRODUCTION"},"httpMethod":"GET","parameters":[{"name":"serviceName","dataType":"string","paramType":"path","fullType":"string","required":true,"description":"The internal name of your overTheBox offer"}],"responseType":"string[]","noAuthentication":false,"description":"List of backups for this service","iamActions":["overTheBox:apiovh:backups/get"]}],"description":"List the overTheBox.Backup objects"},{"path":"/overTheBox/{serviceName}/backups/{backupId}","operations":[{"apiStatus":{"description":"Stable production version","value":"PRODUCTION"},"httpMethod":"DELETE","parameters":[{"name":"backupId","dataType":"string","paramType":"path","fullType":"string","required":true,"description":"The id of the backup"},{"name":"serviceName","dataType":"string","paramType":"path","fullType":"string","required":true,"description":"The internal name of your overTheBox offer"}],"responseType":"void","noAuthentication":false,"description":"Delete a backup","iamActions":["overTheBox:apiovh:backups/delete"]},{"apiStatus":{"description":"Stable production version","value":"PRODUCTION"},"httpMethod":"GET","parameters":[{"name":"backupId","dataType":"string","paramType":"path","fullType":"string","required":true,"description":"The id of the backup"},{"name":"serviceName","dataType":"string","paramType":"path","fullType":"string","required":true,"description":"The internal name of your overTheBox offer"}],"responseType":"overTheBox.Backup","noAuthentication":false,"description":"Get this object properties","iamActions":["overTheBox:apiovh:backups/get"]}],"description":"Backup"},{"path":"/overTheBox/{serviceName}/cancelResiliation","operations":[{"apiStatus":{"description":"Stable production version","value":"PRODUCTION"},"httpMethod":"POST","parameters":[{"name":"serviceName","dataType":"string","paramType":"path","fullType":"string","required":true,"description":"The internal name of your overTheBox offer"}],"responseType":"void","noAuthentication":false,"description":"Cancel the resiliation of the Service","iamActions":["overTheBox:apiovh:cancelResiliation"]}],"description":"cancelResiliation operations"},{"path":"/overTheBox/{serviceName}/changeContact","operations":[{"apiStatus":{"description":"Stable production version","value":"PRODUCTION"},"httpMethod":"POST","parameters":[{"name":"contactAdmin","dataType":"string","paramType":"body","fullType":"coreTypes.AccountId:string","required":false,"description":"The contact to set as admin contact"},{"name":"contactBilling","dataType":"string","paramType":"body","fullType":"coreTypes.AccountId:string","required":false,"description":"The contact to set as billing contact"},{"name":"contactTech","dataType":"string","paramType":"body","fullType":"coreTypes.AccountId:string","required":false,"description":"The contact to set as tech contact"},{"name":"serviceName","dataType":"string","paramType":"path","fullType":"string","required":true,"description":"The internal name of your overTheBox offer"}],"responseType":"long[]","noAuthentication":false,"description":"Launch a contact change procedure","iamActions":["overTheBox:apiovh:changeContact"]}],"description":"Change the contacts of this service"},{"path":"/overTheBox/{serviceName}/configuration/dhcp/config","operations":[{"apiStatus":{"description":"Alpha version","value":"ALPHA"},"httpMethod":"GET","parameters":[{"name":"serviceName","dataType":"string","paramType":"path","fullType":"string","required":true,"description":"The internal name of your overTheBox offer"}],"responseType":"overthebox.configuration.dhcp.Config[]","noAuthentication":false,"description":"Return the list of DHCP configurations","iamActions":["overTheBox:apiovh:configuration/dhcp/config/get"]},{"apiStatus":{"description":"Alpha version","value":"ALPHA"},"httpMethod":"POST","parameters":[{"name":"serviceName","dataType":"string","paramType":"path","fullType":"string","required":true,"description":"The internal name of your overTheBox offer"},{"dataType":"overthebox.configuration.dhcp.Config","paramType":"body","fullType":"overthebox.configuration.dhcp.Config","required":true,"description":"Request Body"}],"responseType":"overthebox.configuration.dhcp.Config","noAuthentication":false,"description":"Create a DHCP configuration","iamActions":["overTheBox:apiovh:configuration/dhcp/config/create"]}],"description":""},{"path":"/overTheBox/{serviceName}/configuration/dhcp/config/{id}","operations":[{"apiStatus":{"description":"Alpha version","value":"ALPHA"},"httpMethod":"DELETE","parameters":[{"name":"serviceName","dataType":"string","paramType":"path","fullType":"string","required":true,"description":"The internal name of your overTheBox offer"},{"name":"id","dataType":"uuid","paramType":"path","fullType":"uuid","required":true,"description":"Id"}],"responseType":"void","noAuthentication":false,"description":"Delete a DHCP configuration","iamActions":["overTheBox:apiovh:configuration/dhcp/config/delete"]},{"apiStatus":{"description":"Alpha version","value":"ALPHA"},"httpMethod":"GET","parameters":[{"name":"serviceName","dataType":"string","paramType":"path","fullType":"string","required":true,"description":"The internal name of your overTheBox offer"},{"name":"id","dataType":"uuid","paramType":"path","fullType":"uuid","required":true,"description":"Id"}],"responseType":"overthebox.configuration.dhcp.Config","noAuthentication":false,"description":"Return the specified DHCP configuration","iamActions":["overTheBox:apiovh:configuration/dhcp/config/get"]},{"apiStatus":{"description":"Alpha version","value":"ALPHA"},"httpMethod":"PUT","parameters":[{"name":"serviceName","dataType":"string","paramType":"path","fullType":"string","required":true,"description":"The internal name of your overTheBox offer"},{"dataType":"overthebox.configuration.dhcp.Config","paramType":"body","fullType":"overthebox.configuration.dhcp.Config","required":true,"description":"Request Body"},{"name":"id","dataType":"uuid","paramType":"path","fullType":"uuid","required":true,"description":"Id"}],"responseType":"overthebox.configuration.dhcp.Config","noAuthentication":false,"description":"Update a DHCP configuration","iamActions":["overTheBox:apiovh:configuration/dhcp/config/edit"]}],"description":""},{"path":"/overTheBox/{serviceName}/configuration/dhcp/staticLease","operations":[{"apiStatus":{"description":"Alpha version","value":"ALPHA"},"httpMethod":"GET","parameters":[{"name":"serviceName","dataType":"string","paramType":"path","fullType":"string","required":true,"description":"The internal name of your overTheBox offer"}],"responseType":"overthebox.configuration.dhcp.StaticLease[]","noAuthentication":false,"description":"Return the list of DHCP static leases","iamActions":["overTheBox:apiovh:configuration/dhcp/staticLease/get"]},{"apiStatus":{"description":"Alpha version","value":"ALPHA"},"httpMethod":"POST","parameters":[{"name":"serviceName","dataType":"string","paramType":"path","fullType":"string","required":true,"description":"The internal name of your overTheBox offer"},{"dataType":"overthebox.configuration.dhcp.StaticLease","paramType":"body","fullType":"overthebox.configuration.dhcp.StaticLease","required":true,"description":"Request Body"}],"responseType":"overthebox.configuration.dhcp.StaticLease","noAuthentication":false,"description":"Create a DHCP static lease","iamActions":["overTheBox:apiovh:configuration/dhcp/staticLease/create"]}],"description":""},{"path":"/overTheBox/{serviceName}/configuration/dhcp/staticLease/{id}","operations":[{"apiStatus":{"description":"Alpha version","value":"ALPHA"},"httpMethod":"DELETE","parameters":[{"name":"serviceName","dataType":"string","paramType":"path","fullType":"string","required":true,"description":"The internal name of your overTheBox offer"},{"name":"id","dataType":"uuid","paramType":"path","fullType":"uuid","required":true,"description":"Id"}],"responseType":"void","noAuthentication":false,"description":"Delete a DHCP static lease","iamActions":["overTheBox:apiovh:configuration/dhcp/staticLease/delete"]},{"apiStatus":{"description":"Alpha version","value":"ALPHA"},"httpMethod":"GET","parameters":[{"name":"serviceName","dataType":"string","paramType":"path","fullType":"string","required":true,"description":"The internal name of your overTheBox offer"},{"name":"id","dataType":"uuid","paramType":"path","fullType":"uuid","required":true,"description":"Id"}],"responseType":"overthebox.configuration.dhcp.StaticLease","noAuthentication":false,"description":"Return the specified DHCP static lease","iamActions":["overTheBox:apiovh:configuration/dhcp/staticLease/get"]},{"apiStatus":{"description":"Alpha version","value":"ALPHA"},"httpMethod":"PUT","parameters":[{"name":"serviceName","dataType":"string","paramType":"path","fullType":"string","required":true,"description":"The internal name of your overTheBox offer"},{"dataType":"overthebox.configuration.dhcp.StaticLease","paramType":"body","fullType":"overthebox.configuration.dhcp.StaticLease","required":true,"description":"Request Body"},{"name":"id","dataType":"uuid","paramType":"path","fullType":"uuid","required":true,"description":"Id"}],"responseType":"overthebox.configuration.dhcp.StaticLease","noAuthentication":false,"description":"Update a DHCP static lease","iamActions":["overTheBox:apiovh:configuration/dhcp/staticLease/edit"]}],"description":""},{"path":"/overTheBox/{serviceName}/configuration/dns/localDomain","operations":[{"apiStatus":{"description":"Alpha version","value":"ALPHA"},"httpMethod":"GET","parameters":[{"name":"serviceName","dataType":"string","paramType":"path","fullType":"string","required":true,"description":"The internal name of your overTheBox offer"}],"responseType":"overthebox.configuration.dns.LocalDomain[]","noAuthentication":false,"description":"Return the list of DNS local domains","iamActions":["overTheBox:apiovh:configuration/dns/localDomain/get"]},{"apiStatus":{"description":"Alpha version","value":"ALPHA"},"httpMethod":"POST","parameters":[{"name":"serviceName","dataType":"string","paramType":"path","fullType":"string","required":true,"description":"The internal name of your overTheBox offer"},{"dataType":"overthebox.configuration.dns.LocalDomain","paramType":"body","fullType":"overthebox.configuration.dns.LocalDomain","required":true,"description":"Request Body"}],"responseType":"overthebox.configuration.dns.LocalDomain","noAuthentication":false,"description":"Create a DNS local domain","iamActions":["overTheBox:apiovh:configuration/dns/localDomain/create"]}],"description":"Local domains"},{"path":"/overTheBox/{serviceName}/configuration/dns/localDomain/{id}","operations":[{"apiStatus":{"description":"Alpha version","value":"ALPHA"},"httpMethod":"DELETE","parameters":[{"name":"serviceName","dataType":"string","paramType":"path","fullType":"string","required":true,"description":"The internal name of your overTheBox offer"},{"name":"id","dataType":"uuid","paramType":"path","fullType":"uuid","required":true,"description":"Id"}],"responseType":"void","noAuthentication":false,"description":"Delete a DNS local domain","iamActions":["overTheBox:apiovh:configuration/dns/localDomain/delete"]},{"apiStatus":{"description":"Alpha version","value":"ALPHA"},"httpMethod":"GET","parameters":[{"name":"serviceName","dataType":"string","paramType":"path","fullType":"string","required":true,"description":"The internal name of your overTheBox offer"},{"name":"id","dataType":"uuid","paramType":"path","fullType":"uuid","required":true,"description":"Id"}],"responseType":"overthebox.configuration.dns.LocalDomain","noAuthentication":false,"description":"Return the specified DNS local domain","iamActions":["overTheBox:apiovh:configuration/dns/localDomain/get"]},{"apiStatus":{"description":"Alpha version","value":"ALPHA"},"httpMethod":"PUT","parameters":[{"name":"serviceName","dataType":"string","paramType":"path","fullType":"string","required":true,"description":"The internal name of your overTheBox offer"},{"dataType":"overthebox.configuration.dns.LocalDomain","paramType":"body","fullType":"overthebox.configuration.dns.LocalDomain","required":true,"description":"Request Body"},{"name":"id","dataType":"uuid","paramType":"path","fullType":"uuid","required":true,"description":"Id"}],"responseType":"overthebox.configuration.dns.LocalDomain","noAuthentication":false,"description":"Update a DNS local domain","iamActions":["overTheBox:apiovh:configuration/dns/localDomain/edit"]}],"description":"Local domains"},{"path":"/overTheBox/{serviceName}/configuration/dns/nameserver","operations":[{"apiStatus":{"description":"Alpha version","value":"ALPHA"},"httpMethod":"GET","parameters":[{"name":"serviceName","dataType":"string","paramType":"path","fullType":"string","required":true,"description":"The internal name of your overTheBox offer"}],"responseType":"overthebox.configuration.dns.Nameserver[]","noAuthentication":false,"description":"Return the list of DNS nameservers","iamActions":["overTheBox:apiovh:configuration/dns/nameserver/get"]},{"apiStatus":{"description":"Alpha version","value":"ALPHA"},"httpMethod":"POST","parameters":[{"name":"serviceName","dataType":"string","paramType":"path","fullType":"string","required":true,"description":"The internal name of your overTheBox offer"},{"dataType":"overthebox.configuration.dns.Nameserver","paramType":"body","fullType":"overthebox.configuration.dns.Nameserver","required":true,"description":"Request Body"}],"responseType":"overthebox.configuration.dns.Nameserver","noAuthentication":false,"description":"Create a DNS nameserver","iamActions":["overTheBox:apiovh:configuration/dns/nameserver/create"]}],"description":""},{"path":"/overTheBox/{serviceName}/configuration/dns/nameserver/{id}","operations":[{"apiStatus":{"description":"Alpha version","value":"ALPHA"},"httpMethod":"DELETE","parameters":[{"name":"serviceName","dataType":"string","paramType":"path","fullType":"string","required":true,"description":"The internal name of your overTheBox offer"},{"name":"id","dataType":"uuid","paramType":"path","fullType":"uuid","required":true,"description":"Id"}],"responseType":"void","noAuthentication":false,"description":"Delete a DNS nameserver","iamActions":["overTheBox:apiovh:configuration/dns/nameserver/delete"]},{"apiStatus":{"description":"Alpha version","value":"ALPHA"},"httpMethod":"GET","parameters":[{"name":"serviceName","dataType":"string","paramType":"path","fullType":"string","required":true,"description":"The internal name of your overTheBox offer"},{"name":"id","dataType":"uuid","paramType":"path","fullType":"uuid","required":true,"description":"Id"}],"responseType":"overthebox.configuration.dns.Nameserver","noAuthentication":false,"description":"Get a DNS nameserver configuration","iamActions":["overTheBox:apiovh:configuration/dns/nameserver/get"]},{"apiStatus":{"description":"Alpha version","value":"ALPHA"},"httpMethod":"PUT","parameters":[{"name":"serviceName","dataType":"string","paramType":"path","fullType":"string","required":true,"description":"The internal name of your overTheBox offer"},{"dataType":"overthebox.configuration.dns.Nameserver","paramType":"body","fullType":"overthebox.configuration.dns.Nameserver","required":true,"description":"Request Body"},{"name":"id","dataType":"uuid","paramType":"path","fullType":"uuid","required":true,"description":"Id"}],"responseType":"overthebox.configuration.dns.Nameserver","noAuthentication":false,"description":"Update a DNS nameserver configuration","iamActions":["overTheBox:apiovh:configuration/dns/nameserver/edit"]}],"description":""},{"path":"/overTheBox/{serviceName}/configuration/firewall/redirect","operations":[{"apiStatus":{"description":"Alpha version","value":"ALPHA"},"httpMethod":"GET","parameters":[{"name":"serviceName","dataType":"string","paramType":"path","fullType":"string","required":true,"description":"The internal name of your overTheBox offer"}],"responseType":"overthebox.configuration.firewall.Redirect[]","noAuthentication":false,"description":"Return the list of firewall redirects","iamActions":["overTheBox:apiovh:configuration/firewall/redirect/get"]},{"apiStatus":{"description":"Alpha version","value":"ALPHA"},"httpMethod":"POST","parameters":[{"name":"serviceName","dataType":"string","paramType":"path","fullType":"string","required":true,"description":"The internal name of your overTheBox offer"},{"dataType":"overthebox.configuration.firewall.Redirect","paramType":"body","fullType":"overthebox.configuration.firewall.Redirect","required":true,"description":"Request Body"}],"responseType":"overthebox.configuration.firewall.Redirect","noAuthentication":false,"description":"Create a firewall redirect","iamActions":["overTheBox:apiovh:configuration/firewall/redirect/create"]}],"description":""},{"path":"/overTheBox/{serviceName}/configuration/firewall/redirect/{id}","operations":[{"apiStatus":{"description":"Alpha version","value":"ALPHA"},"httpMethod":"DELETE","parameters":[{"name":"serviceName","dataType":"string","paramType":"path","fullType":"string","required":true,"description":"The internal name of your overTheBox offer"},{"name":"id","dataType":"uuid","paramType":"path","fullType":"uuid","required":true,"description":"Id"}],"responseType":"void","noAuthentication":false,"description":"Delete a firewall redirect","iamActions":["overTheBox:apiovh:configuration/firewall/redirect/delete"]},{"apiStatus":{"description":"Alpha version","value":"ALPHA"},"httpMethod":"GET","parameters":[{"name":"serviceName","dataType":"string","paramType":"path","fullType":"string","required":true,"description":"The internal name of your overTheBox offer"},{"name":"id","dataType":"uuid","paramType":"path","fullType":"uuid","required":true,"description":"Id"}],"responseType":"overthebox.configuration.firewall.Redirect","noAuthentication":false,"description":"Get a firewall redirect","iamActions":["overTheBox:apiovh:configuration/firewall/redirect/get"]},{"apiStatus":{"description":"Alpha version","value":"ALPHA"},"httpMethod":"PUT","parameters":[{"name":"serviceName","dataType":"string","paramType":"path","fullType":"string","required":true,"description":"The internal name of your overTheBox offer"},{"dataType":"overthebox.configuration.firewall.Redirect","paramType":"body","fullType":"overthebox.configuration.firewall.Redirect","required":true,"description":"Request Body"},{"name":"id","dataType":"uuid","paramType":"path","fullType":"uuid","required":true,"description":"Id"}],"responseType":"overthebox.configuration.firewall.Redirect","noAuthentication":false,"description":"Update a firewall redirect","iamActions":["overTheBox:apiovh:configuration/firewall/redirect/edit"]}],"description":""},{"path":"/overTheBox/{serviceName}/configuration/firewall/rule","operations":[{"apiStatus":{"description":"Alpha version","value":"ALPHA"},"httpMethod":"GET","parameters":[{"name":"serviceName","dataType":"string","paramType":"path","fullType":"string","required":true,"description":"The internal name of your overTheBox offer"}],"responseType":"overthebox.configuration.firewall.Rule[]","noAuthentication":false,"description":"Return the list of firewall rules","iamActions":["overTheBox:apiovh:configuration/firewall/rule/get"]},{"apiStatus":{"description":"Alpha version","value":"ALPHA"},"httpMethod":"POST","parameters":[{"name":"serviceName","dataType":"string","paramType":"path","fullType":"string","required":true,"description":"The internal name of your overTheBox offer"},{"dataType":"overthebox.configuration.firewall.Rule","paramType":"body","fullType":"overthebox.configuration.firewall.Rule","required":true,"description":"Request Body"}],"responseType":"overthebox.configuration.firewall.Rule","noAuthentication":false,"description":"Create a firewall rule","iamActions":["overTheBox:apiovh:configuration/firewall/rule/create"]}],"description":""},{"path":"/overTheBox/{serviceName}/configuration/firewall/rule/{id}","operations":[{"apiStatus":{"description":"Alpha version","value":"ALPHA"},"httpMethod":"DELETE","parameters":[{"name":"serviceName","dataType":"string","paramType":"path","fullType":"string","required":true,"description":"The internal name of your overTheBox offer"},{"name":"id","dataType":"uuid","paramType":"path","fullType":"uuid","required":true,"description":"Id"}],"responseType":"void","noAuthentication":false,"description":"Delete a firewall rule","iamActions":["overTheBox:apiovh:configuration/firewall/rule/delete"]},{"apiStatus":{"description":"Alpha version","value":"ALPHA"},"httpMethod":"GET","parameters":[{"name":"serviceName","dataType":"string","paramType":"path","fullType":"string","required":true,"description":"The internal name of your overTheBox offer"},{"name":"id","dataType":"uuid","paramType":"path","fullType":"uuid","required":true,"description":"Id"}],"responseType":"overthebox.configuration.firewall.Rule","noAuthentication":false,"description":"Get a firewall rule","iamActions":["overTheBox:apiovh:configuration/firewall/rule/get"]},{"apiStatus":{"description":"Alpha version","value":"ALPHA"},"httpMethod":"PUT","parameters":[{"name":"serviceName","dataType":"string","paramType":"path","fullType":"string","required":true,"description":"The internal name of your overTheBox offer"},{"dataType":"overthebox.configuration.firewall.Rule","paramType":"body","fullType":"overthebox.configuration.firewall.Rule","required":true,"description":"Request Body"},{"name":"id","dataType":"uuid","paramType":"path","fullType":"uuid","required":true,"description":"Id"}],"responseType":"overthebox.configuration.firewall.Rule","noAuthentication":false,"description":"Update a firewall rule","iamActions":["overTheBox:apiovh:configuration/firewall/rule/edit"]}],"description":""},{"path":"/overTheBox/{serviceName}/configuration/network/interface","operations":[{"apiStatus":{"description":"Alpha version","value":"ALPHA"},"httpMethod":"GET","parameters":[{"name":"serviceName","dataType":"string","paramType":"path","fullType":"string","required":true,"description":"The internal name of your overTheBox offer"}],"responseType":"overthebox.configuration.network.Interface[]","noAuthentication":false,"description":"Return the list of network interfaces","iamActions":["overTheBox:apiovh:configuration/network/interface/get"]},{"apiStatus":{"description":"Alpha version","value":"ALPHA"},"httpMethod":"POST","parameters":[{"name":"serviceName","dataType":"string","paramType":"path","fullType":"string","required":true,"description":"The internal name of your overTheBox offer"},{"dataType":"overthebox.configuration.network.Interface","paramType":"body","fullType":"overthebox.configuration.network.Interface","required":true,"description":"Request Body"}],"responseType":"overthebox.configuration.network.Interface","noAuthentication":false,"description":"Create a network interface","iamActions":["overTheBox:apiovh:configuration/network/interface/create"]}],"description":""},{"path":"/overTheBox/{serviceName}/configuration/network/interface/{id}","operations":[{"apiStatus":{"description":"Alpha version","value":"ALPHA"},"httpMethod":"DELETE","parameters":[{"name":"serviceName","dataType":"string","paramType":"path","fullType":"string","required":true,"description":"The internal name of your overTheBox offer"},{"name":"id","dataType":"uuid","paramType":"path","fullType":"uuid","required":true,"description":"Id"}],"responseType":"void","noAuthentication":false,"description":"Delete a network interface","iamActions":["overTheBox:apiovh:configuration/network/interface/delete"]},{"apiStatus":{"description":"Alpha version","value":"ALPHA"},"httpMethod":"GET","parameters":[{"name":"serviceName","dataType":"string","paramType":"path","fullType":"string","required":true,"description":"The internal name of your overTheBox offer"},{"name":"id","dataType":"uuid","paramType":"path","fullType":"uuid","required":true,"description":"Id"}],"responseType":"overthebox.configuration.network.Interface","noAuthentication":false,"description":"Get a network interface","iamActions":["overTheBox:apiovh:configuration/network/interface/get"]},{"apiStatus":{"description":"Alpha version","value":"ALPHA"},"httpMethod":"PUT","parameters":[{"name":"serviceName","dataType":"string","paramType":"path","fullType":"string","required":true,"description":"The internal name of your overTheBox offer"},{"dataType":"overthebox.configuration.network.Interface","paramType":"body","fullType":"overthebox.configuration.network.Interface","required":true,"description":"Request Body"},{"name":"id","dataType":"uuid","paramType":"path","fullType":"uuid","required":true,"description":"Id"}],"responseType":"overthebox.configuration.network.Interface","noAuthentication":false,"description":"Update a network interface","iamActions":["overTheBox:apiovh:configuration/network/interface/edit"]}],"description":""},{"path":"/overTheBox/{serviceName}/device","operations":[{"apiStatus":{"description":"Stable production version","value":"PRODUCTION"},"httpMethod":"DELETE","parameters":[{"name":"serviceName","dataType":"string","paramType":"path","fullType":"string","required":true,"description":"The internal name of your overTheBox offer"}],"responseType":"void","noAuthentication":false,"description":"Unlink a device from a service","iamActions":["overTheBox:apiovh:device/delete"]},{"apiStatus":{"description":"Stable production version","value":"PRODUCTION"},"httpMethod":"GET","parameters":[{"name":"serviceName","dataType":"string","paramType":"path","fullType":"string","required":true,"description":"The internal name of your overTheBox offer"}],"responseType":"overTheBox.Device","noAuthentication":false,"description":"Get this object properties","iamActions":["overTheBox:apiovh:device/get"]}],"description":"Device"},{"path":"/overTheBox/{serviceName}/device/actions","operations":[{"apiStatus":{"description":"Stable production version","value":"PRODUCTION"},"httpMethod":"GET","parameters":[{"name":"name","dataType":"string","paramType":"query","fullType":"string","required":false,"description":"Filter the value of name property (=)"},{"name":"serviceName","dataType":"string","paramType":"path","fullType":"string","required":true,"description":"The internal name of your overTheBox offer"},{"name":"status","dataType":"overTheBox.ActionStatusEnum","paramType":"query","fullType":"overTheBox.ActionStatusEnum","required":false,"description":"Filter the value of status property (=)"}],"responseType":"string[]","noAuthentication":false,"description":"List of actions scheduled for this device","iamActions":["overTheBox:apiovh:device/actions/get"]},{"apiStatus":{"description":"Stable production version","value":"PRODUCTION"},"httpMethod":"POST","parameters":[{"name":"name","dataType":"string","paramType":"body","fullType":"string","required":true,"description":"Name of the action"},{"name":"serviceName","dataType":"string","paramType":"path","fullType":"string","required":true,"description":"The internal name of your overTheBox offer"}],"responseType":"overTheBox.DeviceAction","noAuthentication":false,"description":"Create a device action on the device","iamActions":["overTheBox:apiovh:device/actions/create"]}],"description":"List the overTheBox.DeviceAction objects"},{"path":"/overTheBox/{serviceName}/device/actions/{actionId}","operations":[{"apiStatus":{"description":"Stable production version","value":"PRODUCTION"},"httpMethod":"GET","parameters":[{"name":"actionId","dataType":"string","paramType":"path","fullType":"string","required":true,"description":"The id of the action"},{"name":"serviceName","dataType":"string","paramType":"path","fullType":"string","required":true,"description":"The internal name of your overTheBox offer"}],"responseType":"overTheBox.DeviceAction","noAuthentication":false,"description":"Get this object properties","iamActions":["overTheBox:apiovh:device/actions/get"]}],"description":"Device action"},{"path":"/overTheBox/{serviceName}/device/availableActions","operations":[{"apiStatus":{"description":"Stable production version","value":"PRODUCTION"},"httpMethod":"GET","parameters":[{"name":"serviceName","dataType":"string","paramType":"path","fullType":"string","required":true,"description":"The internal name of your overTheBox offer"}],"responseType":"overTheBox.AvailableDeviceAction[]","noAuthentication":false,"description":"List the available device actions","iamActions":["overTheBox:apiovh:device/availableActions/get"]}],"description":"availableActions operations"},{"path":"/overTheBox/{serviceName}/device/backup","operations":[{"apiStatus":{"description":"Stable production version","value":"PRODUCTION"},"httpMethod":"POST","parameters":[{"name":"serviceName","dataType":"string","paramType":"path","fullType":"string","required":true,"description":"The internal name of your overTheBox offer"}],"responseType":"overTheBox.DeviceAction","noAuthentication":false,"description":"Create an action to generate a backup","iamActions":["overTheBox:apiovh:device/backup/create"]}],"description":"backup operations"},{"path":"/overTheBox/{serviceName}/device/logs","operations":[{"apiStatus":{"description":"Stable production version","value":"PRODUCTION"},"httpMethod":"POST","parameters":[{"name":"serviceName","dataType":"string","paramType":"path","fullType":"string","required":true,"description":"The internal name of your overTheBox offer"}],"responseType":"overTheBox.TemporaryLogsLink","noAuthentication":false,"description":"Generate a temporary url to retrieve device logs","iamActions":["overTheBox:apiovh:device/logs/create"]}],"description":"logs operations"},{"path":"/overTheBox/{serviceName}/device/restoreBackup","operations":[{"apiStatus":{"description":"Stable production version","value":"PRODUCTION"},"httpMethod":"POST","parameters":[{"name":"backupId","dataType":"string","paramType":"body","fullType":"string","required":true,"description":"The id of the backup to restore"},{"name":"serviceName","dataType":"string","paramType":"path","fullType":"string","required":true,"description":"The internal name of your overTheBox offer"}],"responseType":"overTheBox.DeviceAction[]","noAuthentication":false,"description":"Create a group of actions to restore a given backup","iamActions":["overTheBox:apiovh:device/restoreBackup"]}],"description":"restoreBackup operations"},{"path":"/overTheBox/{serviceName}/linkDevice","operations":[{"apiStatus":{"description":"Stable production version","value":"PRODUCTION"},"httpMethod":"POST","parameters":[{"name":"deviceId","dataType":"string","paramType":"body","fullType":"string","required":true,"description":"The id of the device"},{"name":"serviceName","dataType":"string","paramType":"path","fullType":"string","required":true,"description":"The internal name of your overTheBox offer"}],"responseType":"void","noAuthentication":false,"description":"Link a device to this service","iamActions":["overTheBox:apiovh:linkDevice"]}],"description":"linkDevice operations"},{"path":"/overTheBox/{serviceName}/linkHardware","operations":[{"apiStatus":{"description":"Stable production version","value":"PRODUCTION"},"httpMethod":"POST","parameters":[{"name":"hardwareName","dataType":"string","paramType":"body","fullType":"string","required":true,"description":"The internal name of your hardware"},{"name":"serviceName","dataType":"string","paramType":"path","fullType":"string","required":true,"description":"The internal name of your overTheBox offer"}],"responseType":"void","noAuthentication":false,"description":"Link an available hardware to this service","iamActions":["overTheBox:apiovh:linkHardware"]}],"description":"linkHardware operations"},{"path":"/overTheBox/{serviceName}/migration/offers","operations":[{"apiStatus":{"description":"Stable production version","value":"PRODUCTION"},"httpMethod":"GET","parameters":[{"name":"serviceName","dataType":"string","paramType":"path","fullType":"string","required":true,"description":"The internal name of your overTheBox offer"}],"responseType":"overTheBox.AvailableMigrationOffer[]","noAuthentication":false,"description":"List all available offers one can migrate to","iamActions":["overTheBox:apiovh:migration/offers/get"]}],"description":"offers operations"},{"path":"/overTheBox/{serviceName}/remoteAccesses","operations":[{"apiStatus":{"description":"Stable production version","value":"PRODUCTION"},"httpMethod":"GET","parameters":[{"name":"serviceName","dataType":"string","paramType":"path","fullType":"string","required":true,"description":"The internal name of your overTheBox offer"}],"responseType":"string[]","noAuthentication":false,"description":"List of remote accesses for the service","iamActions":["overTheBox:apiovh:remoteAccesses/get"]},{"apiStatus":{"description":"Stable production version","value":"PRODUCTION"},"httpMethod":"POST","parameters":[{"name":"allowedIp","dataType":"ipBlock","paramType":"body","fullType":"ipBlock","required":false,"description":"IP block from which the remote access will be allowed (the default value is the IP from which the call is made)"},{"name":"expirationDate","dataType":"datetime","paramType":"body","fullType":"datetime","required":false,"description":"The expirationDate of the remote access (default 1 day)"},{"name":"exposedPort","dataType":"long","paramType":"body","fullType":"long","required":true,"description":"The port that the device will expose"},{"name":"publicKey","dataType":"string","paramType":"body","fullType":"string","required":false,"description":"The remote user public key authorized on the device (for SSH purpose)"},{"name":"serviceName","dataType":"string","paramType":"path","fullType":"string","required":true,"description":"The internal name of your overTheBox offer"}],"responseType":"overTheBox.RemoteAccess","noAuthentication":false,"description":"Create a new remote access for the service","iamActions":["overTheBox:apiovh:remoteAccesses/create"]}],"description":"List the overTheBox.RemoteAccess objects"},{"path":"/overTheBox/{serviceName}/remoteAccesses/{remoteAccessId}","operations":[{"apiStatus":{"description":"Stable production version","value":"PRODUCTION"},"httpMethod":"DELETE","parameters":[{"name":"remoteAccessId","dataType":"string","paramType":"path","fullType":"string","required":true,"description":"The id of the remote access"},{"name":"serviceName","dataType":"string","paramType":"path","fullType":"string","required":true,"description":"The internal name of your overTheBox offer"}],"responseType":"void","noAuthentication":false,"description":"Delete a remote access","iamActions":["overTheBox:apiovh:remoteAccesses/delete"]},{"apiStatus":{"description":"Stable production version","value":"PRODUCTION"},"httpMethod":"GET","parameters":[{"name":"remoteAccessId","dataType":"string","paramType":"path","fullType":"string","required":true,"description":"The id of the remote access"},{"name":"serviceName","dataType":"string","paramType":"path","fullType":"string","required":true,"description":"The internal name of your overTheBox offer"}],"responseType":"overTheBox.RemoteAccess","noAuthentication":false,"description":"Get this object properties","iamActions":["overTheBox:apiovh:remoteAccesses/get"]}],"description":"If authorized, a remote access will expose a port, allowing an access to the device remotely"},{"path":"/overTheBox/{serviceName}/remoteAccesses/{remoteAccessId}/authorize","operations":[{"apiStatus":{"description":"Stable production version","value":"PRODUCTION"},"httpMethod":"POST","parameters":[{"name":"remoteAccessId","dataType":"string","paramType":"path","fullType":"string","required":true,"description":"The id of the remote access"},{"name":"serviceName","dataType":"string","paramType":"path","fullType":"string","required":true,"description":"The internal name of your overTheBox offer"}],"responseType":"void","noAuthentication":false,"description":"Authorize the remote access","iamActions":["overTheBox:apiovh:remoteAccesses/authorize"]}],"description":"authorize operations"},{"path":"/overTheBox/{serviceName}/serviceInfos","operations":[{"apiStatus":{"description":"Stable production version","value":"PRODUCTION"},"httpMethod":"GET","parameters":[{"name":"serviceName","dataType":"string","paramType":"path","fullType":"string","required":true,"description":"The internal name of your overTheBox offer"}],"responseType":"services.Service","noAuthentication":false,"description":"Get this object properties","iamActions":["overTheBox:apiovh:serviceInfos/get"]},{"apiStatus":{"description":"Stable production version","value":"PRODUCTION"},"httpMethod":"PUT","parameters":[{"dataType":"services.Service","paramType":"body","fullType":"services.Service","required":true,"description":"New object properties"},{"name":"serviceName","dataType":"string","paramType":"path","fullType":"string","required":true,"description":"The internal name of your overTheBox offer"}],"responseType":"void","noAuthentication":false,"description":"Alter this object properties","iamActions":["overTheBox:apiovh:serviceInfos/edit"]}],"description":"Details about a Service"},{"path":"/overTheBox/{serviceName}/statistics","operations":[{"apiStatus":{"description":"Beta version","value":"BETA"},"httpMethod":"GET","parameters":[{"name":"serviceName","dataType":"string","paramType":"path","fullType":"string","required":true,"description":"The internal name of your overTheBox offer"},{"name":"metricsType","dataType":"otb.DeviceStatisticsTypeEnum","paramType":"query","fullType":"otb.DeviceStatisticsTypeEnum","required":true,"description":"Type of metrics you want to retrieve"},{"name":"period","dataType":"otb.DeviceStatisticsPeriodEnum","paramType":"query","fullType":"otb.DeviceStatisticsPeriodEnum","required":false,"description":"Period (default is daily)"}],"responseType":"otb.device.statistics[]","noAuthentication":false,"description":"Get statistics for an OTB device","iamActions":["overTheBox:apiovh:statistics/get"]}],"description":"Get statistics for an OTB device"},{"path":"/overTheBox/{serviceName}/tasks","operations":[{"apiStatus":{"description":"Stable production version","value":"PRODUCTION"},"httpMethod":"GET","parameters":[{"name":"name","dataType":"string","paramType":"query","fullType":"string","required":false,"description":"Filter the value of name property (=)"},{"name":"serviceName","dataType":"string","paramType":"path","fullType":"string","required":true,"description":"The internal name of your overTheBox offer"},{"name":"status","dataType":"overTheBox.TaskStatusEnum","paramType":"query","fullType":"overTheBox.TaskStatusEnum","required":false,"description":"Filter the value of status property (=)"}],"responseType":"string[]","noAuthentication":false,"description":"List of tasks scheduled for this service","iamActions":["overTheBox:apiovh:tasks/get"]}],"description":"List the overTheBox.Task objects"},{"path":"/overTheBox/{serviceName}/tasks/{taskId}","operations":[{"apiStatus":{"description":"Stable production version","value":"PRODUCTION"},"httpMethod":"GET","parameters":[{"name":"serviceName","dataType":"string","paramType":"path","fullType":"string","required":true,"description":"The internal name of your overTheBox offer"},{"name":"taskId","dataType":"string","paramType":"path","fullType":"string","required":true,"description":"The id of the task"}],"responseType":"overTheBox.Task","noAuthentication":false,"description":"Get this object properties","iamActions":["overTheBox:apiovh:tasks/get"]}],"description":"Task"}],"resourcePath":"/overTheBox","basePath":"https://api.ovh.com/1.0","models":{"order.CurrencyCodeEnum":{"id":"CurrencyCodeEnum","namespace":"order","enum":["AUD","CAD","CZK","EUR","GBP","INR","LTL","MAD","N/A","PLN","SGD","TND","USD","XOF","points"],"enumType":"string"},"order.Price":{"id":"Price","namespace":"order","description":"Price with it's currency and textual representation","properties":{"currencyCode":{"type":"order.CurrencyCodeEnum","canBeNull":false,"readOnly":false,"required":false},"text":{"type":"string","canBeNull":false,"readOnly":false,"required":false},"value":{"type":"double","canBeNull":false,"readOnly":false,"required":false}}},"otb.DeviceStatisticsPeriodEnum":{"id":"DeviceStatisticsPeriodEnum","namespace":"otb","description":"Statistics Period","enum":["daily","hourly","monthly","weekly"],"enumType":"string"},"otb.DeviceStatisticsTypeEnum":{"id":"DeviceStatisticsTypeEnum","namespace":"otb","description":"Serie Name","enum":["load","memory_free","traffic"],"enumType":"string"},"otb.DeviceStatisticsUnitEnum":{"id":"DeviceStatisticsUnitEnum","namespace":"otb","description":"Serie Unit","enum":["bps","byte","n/a"],"enumType":"string"},"otb.device.statistics":{"id":"statistics","namespace":"otb.device","description":"Device Statistics Datapoints","properties":{"name":{"type":"string","fullType":"string","canBeNull":false,"readOnly":true,"description":"Name of the serie","required":false},"points":{"type":"otb.device.statistics.point[]","fullType":"otb.device.statistics.point[]","canBeNull":false,"readOnly":true,"description":"List of point","required":false},"tags":{"type":"otb.device.statistics.tag[]","fullType":"otb.device.statistics.tag[]","canBeNull":false,"readOnly":true,"description":"List of tags","required":false},"unit":{"type":"otb.DeviceStatisticsUnitEnum","fullType":"otb.DeviceStatisticsUnitEnum","canBeNull":false,"readOnly":true,"description":"Unit of the serie","required":false}}},"otb.device.statistics.point":{"id":"point","namespace":"otb.device.statistics","description":"Statistics Datapoint","properties":{"timestamp":{"type":"long","fullType":"long","canBeNull":false,"readOnly":true,"description":"Timestamp","required":false},"value":{"type":"double","fullType":"double","canBeNull":true,"readOnly":true,"description":"Datapoint value","required":false}}},"otb.device.statistics.tag":{"id":"tag","namespace":"otb.device.statistics","description":"Tags for the metrics","properties":{"name":{"type":"string","fullType":"string","canBeNull":false,"readOnly":true,"description":"Name of tag","required":false},"value":{"type":"string","fullType":"string","canBeNull":true,"readOnly":true,"description":"Value of tag","required":false}}},"overTheBox.ActionStatusEnum":{"id":"ActionStatusEnum","namespace":"overTheBox","description":"Status of a task.","enum":["doing","done","error","todo"],"enumType":"string"},"overTheBox.AvailableDeviceAction":{"id":"AvailableDeviceAction","namespace":"overTheBox","description":"Device action","properties":{"description":{"type":"string","canBeNull":false,"readOnly":false,"description":"Description of the action","required":false},"name":{"type":"string","canBeNull":false,"readOnly":false,"description":"Name of the action","required":false}}},"overTheBox.AvailableMigrationOffer":{"id":"AvailableMigrationOffer","namespace":"overTheBox","description":"Migration offer","properties":{"currentOfferPrice":{"type":"order.Price","canBeNull":false,"readOnly":false,"description":"Monthly price of the current offer","required":false},"description":{"type":"string","canBeNull":false,"readOnly":false,"description":"Description of the offer","required":false},"engagementMonths":{"type":"long","canBeNull":false,"readOnly":false,"description":"Number of months of engagement","required":false},"hardwareAvailable":{"type":"boolean","canBeNull":false,"readOnly":false,"description":"Specify if a hardware is available","required":false},"offer":{"type":"string","canBeNull":false,"readOnly":false,"description":"Name of the offer","required":false},"price":{"type":"order.Price","canBeNull":false,"readOnly":false,"description":"Monthly price of the new offer","required":false}}},"overTheBox.AvailableStatusEnum":{"id":"AvailableStatusEnum","namespace":"overTheBox","description":"Status of the service","enum":["disabled","enabled"],"enumType":"string"},"overTheBox.Backup":{"id":"Backup","namespace":"overTheBox","description":"Backup","properties":{"backupId":{"type":"string","fullType":"string","canBeNull":false,"readOnly":true,"description":"The id of the backup","required":false},"createdAt":{"type":"datetime","fullType":"datetime","canBeNull":false,"readOnly":true,"description":"Date of the creation of the backup","required":false},"deviceActionId":{"type":"string","fullType":"string","canBeNull":true,"readOnly":true,"description":"The id of the device action that triggered the backup","required":false}}},"overTheBox.Device":{"id":"Device","namespace":"overTheBox","description":"Device","properties":{"activated":{"type":"boolean","fullType":"boolean","canBeNull":false,"readOnly":true,"description":"Whether or not this device is associated to a service","required":false},"deviceId":{"type":"string","fullType":"string","canBeNull":false,"readOnly":true,"description":"The id of the device","required":false},"lastSeen":{"type":"datetime","fullType":"datetime","canBeNull":false,"readOnly":true,"description":"Last time the device has been seen on the provisionning servers","required":false},"networkInterfaces":{"type":"overTheBox.DeviceInterface[]","fullType":"overTheBox.DeviceInterface[]","canBeNull":false,"readOnly":true,"description":"Network interfaces of the device","required":false},"publicIp":{"type":"ip","fullType":"ip","canBeNull":false,"readOnly":true,"description":"The public IP of the device","required":false},"systemVersion":{"type":"string","fullType":"string","canBeNull":false,"readOnly":true,"description":"System version of the device","required":false},"version":{"type":"string","fullType":"string","canBeNull":false,"readOnly":true,"description":"Version of the device","required":false}}},"overTheBox.DeviceAction":{"id":"DeviceAction","namespace":"overTheBox","description":"Device action","properties":{"actionId":{"type":"string","fullType":"string","canBeNull":false,"readOnly":true,"description":"The id of the action","required":false},"createdAt":{"type":"datetime","fullType":"datetime","canBeNull":false,"readOnly":true,"description":"Date of creation of the action","required":false},"details":{"type":"string","fullType":"string","canBeNull":false,"readOnly":true,"description":"The details of the action","required":false},"name":{"type":"string","fullType":"string","canBeNull":false,"readOnly":true,"description":"The name of the action","required":false},"status":{"type":"overTheBox.ActionStatusEnum","fullType":"overTheBox.ActionStatusEnum","canBeNull":false,"readOnly":true,"description":"The status of the action","required":false},"todoDate":{"type":"datetime","fullType":"datetime","canBeNull":false,"readOnly":true,"description":"Date of execution of the action","required":false},"updatedAt":{"type":"datetime","fullType":"datetime","canBeNull":false,"readOnly":true,"description":"Last time the action was updated","required":false}}},"overTheBox.DeviceForRegistration":{"id":"DeviceForRegistration","namespace":"overTheBox","description":"A device for registration","properties":{"activated":{"type":"boolean","canBeNull":false,"readOnly":false,"description":"Whether or not this device is actived","required":false},"deviceId":{"type":"string","canBeNull":false,"readOnly":false,"required":false},"lastSeen":{"type":"datetime","canBeNull":false,"readOnly":false,"description":"The last time this device was seen on the provisionning servers","required":false}}},"overTheBox.DeviceInterface":{"id":"DeviceInterface","namespace":"overTheBox","description":"Infos about a network interface","properties":{"device":{"type":"string","canBeNull":true,"readOnly":false,"description":"Device of the interface","required":false},"dnsServers":{"type":"ip[]","canBeNull":true,"readOnly":false,"description":"The DNS servers of this interface","required":false},"gateway":{"type":"ip","canBeNull":true,"readOnly":false,"description":"Gateway of the interface","required":false},"ip":{"type":"ip","canBeNull":true,"readOnly":false,"description":"IP of the interface","required":false},"multipathStatus":{"type":"overTheBox.MultipathStatusEnum","canBeNull":false,"readOnly":false,"description":"Status of MPTCP on this interface","required":false},"name":{"type":"string","canBeNull":false,"readOnly":false,"description":"Name of the interface","required":false},"netmask":{"type":"ip","canBeNull":true,"readOnly":false,"description":"Netmask of the interface","required":false},"publicIp":{"type":"ip","canBeNull":true,"readOnly":false,"description":"Public IP of the interface","required":false}}},"overTheBox.GraphEndpoint":{"id":"GraphEndpoint","namespace":"overTheBox","description":"Parameters required to query metrics from OpenTSDB","properties":{"host":{"type":"string","canBeNull":false,"readOnly":false,"description":"The OpenTSDB host","required":false},"readToken":{"type":"string","canBeNull":false,"readOnly":false,"description":"A read-only token","required":false},"readTokenID":{"type":"string","canBeNull":false,"readOnly":false,"description":"The read-only token ID","required":false}}},"overTheBox.Hardware":{"id":"Hardware","namespace":"overTheBox","description":"Hardware properties","properties":{"canBeLinkedToService":{"type":"boolean","fullType":"boolean","canBeNull":false,"readOnly":true,"description":"True if hardware can be linked to a service without deviceID","required":false},"mac":{"type":"macAddress","fullType":"macAddress","canBeNull":true,"readOnly":true,"description":"Hardware MAC address","required":false},"model":{"type":"string","fullType":"string","canBeNull":false,"readOnly":true,"description":"Hardware model","required":false},"name":{"type":"string","fullType":"string","canBeNull":false,"readOnly":true,"description":"Hardware name","required":false},"serial":{"type":"string","fullType":"string","canBeNull":false,"readOnly":true,"description":"Hardware serial","required":false}}},"overTheBox.MultipathStatusEnum":{"id":"MultipathStatusEnum","namespace":"overTheBox","description":"Status of a MPTCP Interface.","enum":["backup","handover","master","off","on"],"enumType":"string"},"overTheBox.RemoteAccess":{"id":"RemoteAccess","namespace":"overTheBox","description":"If authorized, a remote access will expose a port, allowing an access to the device remotely","properties":{"accepted":{"type":"boolean","fullType":"boolean","canBeNull":false,"readOnly":true,"description":"If the remote access was accepted by the remote user","required":false},"askDate":{"type":"datetime","fullType":"datetime","canBeNull":false,"readOnly":true,"description":"The date of the remote access demand","required":false},"authorizedBy":{"type":"string","fullType":"string","canBeNull":true,"readOnly":true,"description":"The user that authorized the remote access","required":false},"connectionInfos":{"type":"overTheBox.RemoteAccessConnectionInfos","fullType":"overTheBox.RemoteAccessConnectionInfos","canBeNull":false,"readOnly":true,"description":"All the infos needed to connect yourself to your OTB","required":false},"expirationDate":{"type":"datetime","fullType":"datetime","canBeNull":false,"readOnly":true,"description":"When the remote access will be automatically deleted","required":false},"exposedPort":{"type":"long","fullType":"long","canBeNull":false,"readOnly":true,"description":"The device's port which will be exposed","required":false},"remoteAccessId":{"type":"string","fullType":"string","canBeNull":false,"readOnly":true,"description":"The id of the remote access","required":false},"remoteUserInfos":{"type":"overTheBox.RemoteAccessUserInfos","fullType":"overTheBox.RemoteAccessUserInfos","canBeNull":false,"readOnly":true,"description":"Infos about the remote user","required":false},"status":{"type":"overTheBox.RemoteAccessStatusEnum","fullType":"overTheBox.RemoteAccessStatusEnum","canBeNull":false,"readOnly":true,"description":"Status of the remote access","required":false}}},"overTheBox.RemoteAccessConnectionInfos":{"id":"RemoteAccessConnectionInfos","namespace":"overTheBox","description":"All the infos needed to connect yourself to your OTB","properties":{"ip":{"type":"ip","canBeNull":true,"readOnly":false,"description":"IP to connect to when accessing the device remotely","required":false},"port":{"type":"long","canBeNull":true,"readOnly":false,"description":"Port to connect to when accessing the device remotely","required":false}}},"overTheBox.RemoteAccessStatusEnum":{"id":"RemoteAccessStatusEnum","namespace":"overTheBox","description":"Status of the remote access.","enum":["active","creating","deleted","deleting","pendingValidation","toDelete"],"enumType":"string"},"overTheBox.RemoteAccessUserInfos":{"id":"RemoteAccessUserInfos","namespace":"overTheBox","description":"Infos about the remote user","properties":{"ip":{"type":"ipBlock","canBeNull":false,"readOnly":false,"description":"IP from which the remote access will be allowed","required":false},"publicKey":{"type":"string","canBeNull":true,"readOnly":false,"description":"The public key authorized on the device (for SSH purpose)","required":false},"user":{"type":"string","canBeNull":false,"readOnly":false,"description":"The user that will access the device remotely","required":false}}},"overTheBox.Service":{"id":"Service","namespace":"overTheBox","description":"Service","properties":{"SOCKSProxyEnabled":{"type":"boolean","fullType":"boolean","canBeNull":false,"readOnly":true,"description":"If the socks proxy is enabled","required":false},"autoMTU":{"type":"overTheBox.AvailableStatusEnum","fullType":"overTheBox.AvailableStatusEnum","canBeNull":false,"readOnly":true,"description":"The status of the autoMTU","required":false},"configurationMode":{"type":"overTheBox.ServiceConfigurationModeEnum","fullType":"overTheBox.ServiceConfigurationModeEnum","canBeNull":false,"readOnly":true,"description":"Configuration mode of the service","required":false},"customerDescription":{"type":"string","fullType":"string","canBeNull":true,"readOnly":false,"description":"Editable field for customer","required":false},"graphEndpoint":{"type":"overTheBox.GraphEndpoint","fullType":"overTheBox.GraphEndpoint","canBeNull":true,"readOnly":true,"description":"Parameters needed to fetch metrics","required":false},"releaseChannel":{"type":"string","fullType":"string","canBeNull":false,"readOnly":false,"description":"Release channel of the service","required":false},"serviceName":{"type":"string","fullType":"string","canBeNull":false,"readOnly":true,"description":"The name of the service","required":false},"status":{"type":"overTheBox.ServiceStatusEnum","fullType":"overTheBox.ServiceStatusEnum","canBeNull":false,"readOnly":true,"description":"The status of the service","required":false},"tunnelMode":{"type":"overTheBox.TunnelModeEnum","fullType":"overTheBox.TunnelModeEnum","canBeNull":false,"readOnly":true,"description":"The tunnel mode of the service","required":false}}},"overTheBox.ServiceConfigurationModeEnum":{"id":"ServiceConfigurationModeEnum","namespace":"overTheBox","description":"Configuration mode of the service","enum":["autoconfigure","local"],"enumType":"string"},"overTheBox.ServiceStatusEnum":{"id":"ServiceStatusEnum","namespace":"overTheBox","description":"Status of the service.","enum":["active","creating","deleted","suspended","toCreate","toDelete"],"enumType":"string"},"overTheBox.Task":{"id":"Task","namespace":"overTheBox","description":"Task","properties":{"name":{"type":"string","fullType":"string","canBeNull":false,"readOnly":true,"description":"The name of the task","required":false},"status":{"type":"overTheBox.TaskStatusEnum","fullType":"overTheBox.TaskStatusEnum","canBeNull":false,"readOnly":true,"description":"The status of the task","required":false},"taskId":{"type":"string","fullType":"string","canBeNull":false,"readOnly":true,"description":"The id of the task","required":false}}},"overTheBox.TaskStatusEnum":{"id":"TaskStatusEnum","namespace":"overTheBox","description":"Status of a task.","enum":["doing","done","error","todo"],"enumType":"string"},"overTheBox.TemporaryLogsLink":{"id":"TemporaryLogsLink","namespace":"overTheBox","description":"Temporary url informations","properties":{"expirationDate":{"type":"datetime","canBeNull":false,"readOnly":false,"description":"Temporary url expiration date","required":false},"url":{"type":"string","canBeNull":false,"readOnly":false,"description":"Temporary url","required":false}}},"overTheBox.TunnelModeEnum":{"id":"TunnelModeEnum","namespace":"overTheBox","description":"Tunnel mode of the service.","enum":["glorytun","glorytun_hybrid","glorytun_mud"],"enumType":"string"},"overthebox.configuration.StatusEnum":{"id":"StatusEnum","namespace":"overthebox.configuration","description":"Status of the configuration","enum":["applying","ok","problem","to_apply"],"enumType":"string"},"overthebox.configuration.dhcp.Config":{"id":"Config","namespace":"overthebox.configuration.dhcp","description":"DHCP configuration","properties":{"configuration":{"type":"overthebox.configuration.types.dhcp.Config","fullType":"overthebox.configuration.types.dhcp.Config","canBeNull":false,"readOnly":false,"description":"DHCP configuration","required":false},"id":{"type":"uuid","fullType":"uuid","canBeNull":false,"readOnly":true,"description":"Identifier of the configuration","required":false},"priority":{"type":"long","fullType":"long","canBeNull":false,"readOnly":false,"description":"Priority of application","required":false},"status":{"type":"overthebox.configuration.StatusEnum","fullType":"overthebox.configuration.StatusEnum","canBeNull":false,"readOnly":true,"description":"Status of the configuration on the device","required":false}}},"overthebox.configuration.dhcp.StaticLease":{"id":"StaticLease","namespace":"overthebox.configuration.dhcp","description":"DHCP static lease","properties":{"configuration":{"type":"overthebox.configuration.types.dhcp.StaticLease","fullType":"overthebox.configuration.types.dhcp.StaticLease","canBeNull":false,"readOnly":false,"description":"DHCP static lease","required":false},"id":{"type":"uuid","fullType":"uuid","canBeNull":false,"readOnly":true,"description":"Identifier of the configuration","required":false},"priority":{"type":"long","fullType":"long","canBeNull":false,"readOnly":false,"description":"Priority of application","required":false},"status":{"type":"overthebox.configuration.StatusEnum","fullType":"overthebox.configuration.StatusEnum","canBeNull":false,"readOnly":true,"description":"Status of the configuration on the device","required":false}}},"overthebox.configuration.dns.LocalDomain":{"id":"LocalDomain","namespace":"overthebox.configuration.dns","description":"DNS local domain","properties":{"configuration":{"type":"overthebox.configuration.types.dns.LocalDomain","fullType":"overthebox.configuration.types.dns.LocalDomain","canBeNull":false,"readOnly":false,"description":"DNS local domain","required":false},"id":{"type":"uuid","fullType":"uuid","canBeNull":false,"readOnly":true,"description":"Identifier of the configuration","required":false},"priority":{"type":"long","fullType":"long","canBeNull":false,"readOnly":false,"description":"Priority of application","required":false},"status":{"type":"overthebox.configuration.StatusEnum","fullType":"overthebox.configuration.StatusEnum","canBeNull":false,"readOnly":true,"description":"Status of the configuration on the device","required":false}}},"overthebox.configuration.dns.Nameserver":{"id":"Nameserver","namespace":"overthebox.configuration.dns","description":"DNS nameserver","properties":{"configuration":{"type":"overthebox.configuration.types.dns.Nameserver","fullType":"overthebox.configuration.types.dns.Nameserver","canBeNull":false,"readOnly":false,"description":"DNS nameserver","required":false},"id":{"type":"uuid","fullType":"uuid","canBeNull":false,"readOnly":true,"description":"Identifier of the configuration","required":false},"priority":{"type":"long","fullType":"long","canBeNull":false,"readOnly":false,"description":"Priority of application","required":false},"status":{"type":"overthebox.configuration.StatusEnum","fullType":"overthebox.configuration.StatusEnum","canBeNull":false,"readOnly":true,"description":"Status of the configuration on the device","required":false}}},"overthebox.configuration.firewall.ProtocolEnum":{"id":"ProtocolEnum","namespace":"overthebox.configuration.firewall","description":"Protocol family to match","enum":["ah","all","ax.25","dccp","ddp","egp","eigrp","encap","esp","etherip","fc","ggp","gre","hmp","hopopt","icmp","idpr-cmtp","idrp","igmp","igp","ip","ip-encap","ipcomp","ipip","ipsec-ah","ipsec-esp","ipv6","ipv6-frag","ipv6-icmp","ipv6-nonxt","ipv6-opts","ipv6-route","isis","iso-tp4","l2tp","ospfigp","pim","pup","rdp","rspf","rsvp","sctp","skip","st","tcp","tcpudp","udp","udplite","vmtp","vrrp","xns-idp","xtp"],"enumType":"string"},"overthebox.configuration.firewall.Redirect":{"id":"Redirect","namespace":"overthebox.configuration.firewall","description":"Firewall rule","properties":{"configuration":{"type":"overthebox.configuration.types.firewall.Redirect","fullType":"overthebox.configuration.types.firewall.Redirect","canBeNull":false,"readOnly":false,"description":"Firewall redirect rule","required":false},"id":{"type":"uuid","fullType":"uuid","canBeNull":false,"readOnly":true,"description":"Identifier of the configuration","required":false},"priority":{"type":"long","fullType":"long","canBeNull":false,"readOnly":false,"description":"Priority","required":false},"status":{"type":"overthebox.configuration.StatusEnum","fullType":"overthebox.configuration.StatusEnum","canBeNull":false,"readOnly":true,"description":"Status of the configuration on the device","required":false}}},"overthebox.configuration.firewall.Rule":{"id":"Rule","namespace":"overthebox.configuration.firewall","description":"Firewall rule","properties":{"configuration":{"type":"overthebox.configuration.types.firewall.Rule","fullType":"overthebox.configuration.types.firewall.Rule","canBeNull":false,"readOnly":false,"description":"Firewall rule","required":false},"id":{"type":"uuid","fullType":"uuid","canBeNull":false,"readOnly":true,"description":"Identifier of the configuration","required":false},"priority":{"type":"long","fullType":"long","canBeNull":false,"readOnly":false,"description":"Priority","required":false},"status":{"type":"overthebox.configuration.StatusEnum","fullType":"overthebox.configuration.StatusEnum","canBeNull":false,"readOnly":true,"description":"Status of the configuration on the device","required":false}}},"overthebox.configuration.firewall.redirect.TargetEnum":{"id":"TargetEnum","namespace":"overthebox.configuration.firewall.redirect","description":"Redirection NAT target","enum":["DNAT","SNAT"],"enumType":"string"},"overthebox.configuration.firewall.rule.FamilyEnum":{"id":"FamilyEnum","namespace":"overthebox.configuration.firewall.rule","description":"Protocol family to match","enum":["any","ipv4","ipv6"],"enumType":"string"},"overthebox.configuration.firewall.rule.TargetEnum":{"id":"TargetEnum","namespace":"overthebox.configuration.firewall.rule","description":"Target action","enum":["ACCEPT","DROP","MARK","NOTRACK","REJECT"],"enumType":"string"},"overthebox.configuration.network.Interface":{"id":"Interface","namespace":"overthebox.configuration.network","description":"Network interface","properties":{"configuration":{"type":"overthebox.configuration.types.network.Interface","fullType":"overthebox.configuration.types.network.Interface","canBeNull":false,"readOnly":false,"description":"Network interface","required":true},"id":{"type":"uuid","fullType":"uuid","canBeNull":false,"readOnly":true,"description":"Identifier of the configuration","required":false},"priority":{"type":"long","fullType":"long","canBeNull":false,"readOnly":false,"description":"Priority of application","required":true},"status":{"type":"overthebox.configuration.StatusEnum","fullType":"overthebox.configuration.StatusEnum","canBeNull":false,"readOnly":true,"description":"Status of the configuration on the device","required":false}}},"overthebox.configuration.network.interface.MultipathEnum":{"id":"MultipathEnum","namespace":"overthebox.configuration.network.interface","description":"Multipath mode","enum":["backup","handover","master","off","on"],"enumType":"string"},"overthebox.configuration.network.interface.ProtoEnum":{"id":"ProtoEnum","namespace":"overthebox.configuration.network.interface","description":"IP allocation protocol of the network interface","enum":["dhcp","dhcpv6","static"],"enumType":"string"},"overthebox.configuration.network.interface.TypeEnum":{"id":"TypeEnum","namespace":"overthebox.configuration.network.interface","description":"Type of the network interface","enum":["bridge","inet","inet6"],"enumType":"string"},"overthebox.configuration.types.dhcp.Config":{"id":"Config","namespace":"overthebox.configuration.types.dhcp","description":"DHCP configuration","properties":{"interface":{"type":"string","fullType":"string","canBeNull":false,"readOnly":false,"description":"Name of the interface to apply the DHCP configuration","required":true},"leaseDuration":{"type":"long","fullType":"long","canBeNull":false,"readOnly":false,"description":"Duration of the lease in seconds","required":true},"offset":{"type":"long","fullType":"long","canBeNull":false,"readOnly":false,"description":"Offset from the network address for the first IP of the pool","required":true},"poolSize":{"type":"long","fullType":"long","canBeNull":false,"readOnly":false,"description":"Number of IPs in the pool","required":true}}},"overthebox.configuration.types.dhcp.StaticLease":{"id":"StaticLease","namespace":"overthebox.configuration.types.dhcp","description":"DHCP static lease","properties":{"hostname":{"type":"string","fullType":"string","canBeNull":false,"readOnly":false,"description":"Hostname of the device","required":false},"ip":{"type":"ip","fullType":"ip","canBeNull":false,"readOnly":false,"description":"IP address to associate","required":true},"mac":{"type":"macAddress","fullType":"macAddress","canBeNull":false,"readOnly":false,"description":"Mac adddress of the device","required":true}}},"overthebox.configuration.types.dns.LocalDomain":{"id":"LocalDomain","namespace":"overthebox.configuration.types.dns","description":"DNS local domain","properties":{"hostname":{"type":"string","fullType":"string","canBeNull":false,"readOnly":false,"description":"Hostname","required":true},"ip":{"type":"ip","fullType":"ip","canBeNull":false,"readOnly":false,"description":"IP address associated with the hostname","required":true}}},"overthebox.configuration.types.dns.Nameserver":{"id":"Nameserver","namespace":"overthebox.configuration.types.dns","description":"DNS nameserver","properties":{"server":{"type":"ip","fullType":"ip","canBeNull":false,"readOnly":false,"description":"IP of the DNS nameserver","required":true}}},"overthebox.configuration.types.firewall.Redirect":{"id":"Redirect","namespace":"overthebox.configuration.types.firewall","description":"Firewall redirect","properties":{"destinationIp":{"type":"ip","fullType":"ip","canBeNull":true,"readOnly":false,"description":"Destination IP","required":false},"destinationPort":{"type":"string","fullType":"string","canBeNull":true,"readOnly":false,"description":"Destination port(s) (single value or range separated by - )","required":false},"destinationZone":{"type":"string","fullType":"string","canBeNull":true,"readOnly":false,"description":"Destination zone","required":false},"name":{"type":"string","fullType":"string","canBeNull":false,"readOnly":false,"description":"Name","required":true},"protocol":{"type":"overthebox.configuration.firewall.ProtocolEnum","fullType":"overthebox.configuration.firewall.ProtocolEnum","canBeNull":true,"readOnly":false,"description":"Protocol","required":false},"sourceDestinationIp":{"type":"ip","fullType":"ip","canBeNull":true,"readOnly":false,"description":"Source destination IP","required":false},"sourceDestinationPort":{"type":"string","fullType":"string","canBeNull":true,"readOnly":false,"description":"Source destination port(s) (single value or range separated by - )","required":false},"sourceIp":{"type":"ipBlock","fullType":"ipBlock","canBeNull":true,"readOnly":false,"description":"Source IP","required":false},"sourcePort":{"type":"long","fullType":"long","canBeNull":true,"readOnly":false,"description":"Source port","required":false},"sourceZone":{"type":"string","fullType":"string","canBeNull":false,"readOnly":false,"description":"Source zone","required":true},"target":{"type":"overthebox.configuration.firewall.redirect.TargetEnum","fullType":"overthebox.configuration.firewall.redirect.TargetEnum","canBeNull":true,"readOnly":false,"description":"Target","required":false}}},"overthebox.configuration.types.firewall.Rule":{"id":"Rule","namespace":"overthebox.configuration.types.firewall","description":"Firewall rule","properties":{"destinationIp":{"type":"ipBlock","fullType":"ipBlock","canBeNull":true,"readOnly":false,"description":"Destination IP","required":false},"destinationPort":{"type":"string","fullType":"string","canBeNull":true,"readOnly":false,"description":"Destination port(s) (single value or range separated by - )","required":false},"destinationZone":{"type":"string","fullType":"string","canBeNull":true,"readOnly":false,"description":"Destination zone","required":false},"family":{"type":"overthebox.configuration.firewall.rule.FamilyEnum","fullType":"overthebox.configuration.firewall.rule.FamilyEnum","canBeNull":true,"readOnly":false,"description":"IP family","required":false},"name":{"type":"string","fullType":"string","canBeNull":true,"readOnly":false,"description":"Name of the rule","required":false},"protocol":{"type":"overthebox.configuration.firewall.ProtocolEnum","fullType":"overthebox.configuration.firewall.ProtocolEnum","canBeNull":true,"readOnly":false,"description":"Protocol to match","required":false},"sourceIp":{"type":"ipBlock","fullType":"ipBlock","canBeNull":true,"readOnly":false,"description":"Source IP","required":false},"sourcePort":{"type":"string","fullType":"string","canBeNull":true,"readOnly":false,"description":"Source port(s) (single value or range separated by - )","required":false},"sourceZone":{"type":"string","fullType":"string","canBeNull":false,"readOnly":false,"description":"Source zone","required":false},"target":{"type":"overthebox.configuration.firewall.rule.TargetEnum","fullType":"overthebox.configuration.firewall.rule.TargetEnum","canBeNull":false,"readOnly":false,"description":"Target","required":false}}},"overthebox.configuration.types.network.Interface":{"id":"Interface","namespace":"overthebox.configuration.types.network","description":"Network interface","properties":{"gateway":{"type":"ip","fullType":"ip","canBeNull":true,"readOnly":false,"description":"IP address of the gateway","required":false},"ifname":{"type":"string","fullType":"string","canBeNull":false,"readOnly":false,"description":"Name of the physical interface","required":true},"interfaceName":{"type":"string","fullType":"string","canBeNull":false,"readOnly":false,"description":"Name given to the new interface","required":true},"ip":{"type":"ip","fullType":"ip","canBeNull":true,"readOnly":false,"description":"IP address of the network","required":false},"ipv6":{"type":"boolean","fullType":"boolean","canBeNull":true,"readOnly":false,"description":"Is an IPV6 interface","required":false},"mtu":{"type":"long","fullType":"long","canBeNull":true,"readOnly":false,"description":"MTU of the network","required":false},"multipath":{"type":"overthebox.configuration.network.interface.MultipathEnum","fullType":"overthebox.configuration.network.interface.MultipathEnum","canBeNull":true,"readOnly":false,"description":"Use the interface in multipath","required":false},"netmask":{"type":"ip","fullType":"ip","canBeNull":true,"readOnly":false,"description":"Netmask of the network","required":false},"protocol":{"type":"overthebox.configuration.network.interface.ProtoEnum","fullType":"overthebox.configuration.network.interface.ProtoEnum","canBeNull":true,"readOnly":false,"description":"Protocol for IP allocation","required":false},"routingTable":{"type":"string","fullType":"string","canBeNull":true,"readOnly":false,"description":"Routing table used by the network interface","required":false},"type":{"type":"overthebox.configuration.network.interface.TypeEnum","fullType":"overthebox.configuration.network.interface.TypeEnum","canBeNull":true,"readOnly":false,"description":"Type of the network interface","required":false}}},"price.OverTheBox.OfferEnum":{"id":"OfferEnum","namespace":"price.OverTheBox","description":"Enum of Offers","enum":["plus.v1"],"enumType":"string"},"service.RenewType":{"id":"RenewType","namespace":"service","description":"Map a possible renew for a specific service","properties":{"automatic":{"type":"boolean","canBeNull":false,"readOnly":false,"description":"The service is automatically renewed","required":false},"deleteAtExpiration":{"type":"boolean","canBeNull":false,"readOnly":false,"description":"The service will be deleted at expiration","required":false},"forced":{"type":"boolean","canBeNull":false,"readOnly":false,"description":"The service forced to be renewed","required":false},"manualPayment":{"type":"boolean","canBeNull":true,"readOnly":false,"description":"The service needs to be manually renewed and paid","required":false},"period":{"type":"long","canBeNull":true,"readOnly":false,"description":"period of renew in month","required":false}}},"service.RenewalTypeEnum":{"id":"RenewalTypeEnum","namespace":"service","description":"Detailed renewal type of a service","enum":["automaticForcedProduct","automaticV2012","automaticV2014","automaticV2016","manual","oneShot","option"],"enumType":"string"},"service.StateEnum":{"id":"StateEnum","namespace":"service","enum":["expired","inCreation","ok","pendingDebt","unPaid"],"enumType":"string"},"services.Service":{"id":"Service","namespace":"services","description":"Details about a Service","properties":{"canDeleteAtExpiration":{"type":"boolean","fullType":"boolean","canBeNull":false,"readOnly":true,"description":"Indicates that the service can be set up to be deleted at expiration","required":false},"contactAdmin":{"type":"string","fullType":"coreTypes.AccountId:string","canBeNull":false,"readOnly":true,"required":false},"contactBilling":{"type":"string","fullType":"coreTypes.AccountId:string","canBeNull":false,"readOnly":true,"required":false},"contactTech":{"type":"string","fullType":"coreTypes.AccountId:string","canBeNull":false,"readOnly":true,"required":false},"creation":{"type":"date","fullType":"date","canBeNull":false,"readOnly":true,"required":false},"domain":{"type":"string","fullType":"string","canBeNull":false,"readOnly":true,"required":false},"engagedUpTo":{"type":"date","fullType":"date","canBeNull":true,"readOnly":true,"required":false},"expiration":{"type":"date","fullType":"date","canBeNull":false,"readOnly":true,"required":false},"possibleRenewPeriod":{"type":"long[]","fullType":"long[]","canBeNull":true,"readOnly":true,"description":"All the possible renew period of your service in month","required":false},"renew":{"type":"service.RenewType","fullType":"service.RenewType","canBeNull":true,"readOnly":false,"description":"Way of handling the renew","required":false},"renewalType":{"type":"service.RenewalTypeEnum","fullType":"service.RenewalTypeEnum","canBeNull":false,"readOnly":true,"required":false},"serviceId":{"type":"long","fullType":"coreTypes.ServiceId:long","canBeNull":false,"readOnly":true,"required":false},"status":{"type":"service.StateEnum","fullType":"service.StateEnum","canBeNull":false,"readOnly":true,"required":false}}}}}
